my_own_package/__init__.py
Marius_baraian-0.2.0.dist-info/METADATA
Marius_baraian-0.2.0.dist-info/WHEEL
Marius_baraian-0.2.0.dist-info/top_level.txt
Marius_baraian-0.2.0.dist-info/RECORD
