Metadata-Version: 2.1
Name: Marius-baraian
Version: 0.2.0
Summary: This is my first package
Home-page: UNKNOWN
Author: Baraian Marius
Author-email: marius.baraian08@gmail.com
License: UNKNOWN
Platform: UNKNOWN
